retemplate/__init__.py
retemplate-0.0.2.data/scripts/rtpl
retemplate-0.0.2.dist-info/LICENSE
retemplate-0.0.2.dist-info/METADATA
retemplate-0.0.2.dist-info/WHEEL
retemplate-0.0.2.dist-info/top_level.txt
retemplate-0.0.2.dist-info/RECORD
