Metadata-Version: 2.1
Name: retemplate
Version: 0.0.2
Summary: A module to execute a Jinja template on a schedule, supporting several backends for value storage
Home-page: https://github.com/ryanjjung/retemplate
Author: Ryan Jung
Author-email: ryanjjung@gmail.com
License: Apache License 2.0
Platform: UNKNOWN
